togglecase/__init__.py
togglecase-0.1.dist-info/LICENSE.txt
togglecase-0.1.dist-info/METADATA
togglecase-0.1.dist-info/WHEEL
togglecase-0.1.dist-info/top_level.txt
togglecase-0.1.dist-info/RECORD
