Metadata-Version: 2.1
Name: togglecase
Version: 0.1
Summary: It is a wrapper function of swapcase.
Home-page: UNKNOWN
Author: Yash Jain
Author-email: datapoc001@gmail.com
License: MIT
Keywords: SOME,MEANINGFULL,KEYWORDS
Platform: UNKNOWN
Classifier: Development Status :: 3 - Alpha
Classifier: Intended Audience :: Developers
Classifier: Topic :: Software Development :: Build Tools
Classifier: License :: OSI Approved :: MIT License
Classifier: Programming Language :: Python :: 3
Classifier: Programming Language :: Python :: 3.4
Classifier: Programming Language :: Python :: 3.5
Classifier: Programming Language :: Python :: 3.6
Requires-Dist: validators
Requires-Dist: beautifulsoup4
